{"Dont": ["you"], "you": ["love"], "love": ["him"], "him": ["madly"], "madly": ["?"], "?": [], "Appearing": ["tonight"], "tonight": ["&"], "&": ["for"], "for": ["all", "this"], "all": ["eternity"], "eternity": ["in"], "in": ["the", "1923--The", "The"], "the": ["cemetery", "stage", "Devine", "lights"], "cemetery": ["lets"], "lets": ["hear"], "hear": ["it"], "it": ["for"], "this": ["Doors", "French", "author", "Little", "great"], "Doors": ["singer"], "singer": ["."], ".": [], "Lets": ["welcome", "turn"], "welcome": ["back"], "back": ["to"], "to": ["the"], "stage": ["this"], "French": ["actress"], "actress": ["who"], "who": ["made"], "made": ["her"], "her": ["exit", "classic"], "exit": ["in"], "1923--The": ["Incredible"], "Incredible": ["the"], "Devine": ["."], "What": ["could"], "could": ["be"], "be": ["more"], "more": ["appropriate"], "appropriate": ["than"], "than": ["this"], "author": ["reading"], "reading": ["selections"], "selections": ["from"], "from": ["his"], "his": ["own", "performance"], "own": ["Remembrance"], "Remembrance": ["of"], "of": ["Things"], "Things": ["Past"], "Past": ["."], "turn": ["the"], "lights": ["down"], "down": ["low"], "low": ["as"], "as": ["this"], "Little": ["Sparrow"], "Sparrow": ["takes"], "takes": ["wing"], "wing": ["again"], "again": ["singing"], "singing": ["her"], "classic": ["La"], "La": ["Vie"], "Vie": ["En"], "En": ["Rose"], "Rose": ["."], "Finally": ["finishing"], "finishing": ["his"], "performance": ["in"], "The": ["Imaginary"], "Imaginary": ["Invalid"], "Invalid": ["its"], "its": ["this"], "great": ["17th"], "17th": ["century"], "century": ["playwright"], "playwright": ["."]}