{"The": ["first", "first", "Atlas", "ICBM"], "first": ["stage", "rockets", "stage", "stage"], "stage": ["of", ".", "that"], "of": ["a", "a", "nergy", "motion", "these", "Goddards", "a", "this", "miles"], "a": ["multi-stage", "cause", "U", "rocket", "rocket", "space", "multistage", "payload", "military"], "multi-stage": ["rocket"], "rocket": ["or", "propelled", "using", "must", "gun", "off", "patents"], "or": ["an"], "an": ["energetic", "example"], "energetic": ["supporter"], "supporter": ["of"], "cause": ["."], ".": [], "Rockets": ["get", "developed"], "get": ["their"], "their": ["forward"], "forward": ["motion"], "motion": ["from", "explain"], "from": ["this"], "this": ["the", "man", "type", "man", "intermediate", "in", "EV", "country", "anti-tank", "first", "can"], "the": ["JP", "red", "last", "LM", "first", "U", "movement", "ground", "Gulf", "U", "U"], "JP": ["in"], "in": ["Cal", "units", "flight", "this"], "Cal": ["Techs"], "Techs": ["JPL"], "JPL": ["."], "developed": ["by", "into"], "by": ["William", "this", "doing", "these"], "William": ["Congreve", "Hales"], "Congreve": ["produced"], "produced": ["the"], "red": ["glare"], "glare": ["this"], "man": ["saw", "whose", "to"], "saw": ["on"], "on": ["Sept", "his"], "Sept": ["."], "13-14": ["1814"], "1814": ["."], "NERVA": ["was"], "was": ["a", "developed"], "U": [".", ".", ".", "."], "S": [".", ".", ".", "."], "project": ["to"], "to": ["develop", "command", "25000", "achieve", "the", "slow", "intercept", "a"], "develop": ["a"], "propelled": ["by"], "type": ["of"], "nergy": ["."], "A": ["rockets"], "rockets": ["thrust", "were", "attached", "as"], "thrust": ["may", "for"], "may": ["be"], "be": ["measured"], "measured": ["in"], "units": ["named"], "named": ["for"], "for": ["this", "short", "takeoffs", "this", "infringements"], "whose": ["laws"], "laws": ["of"], "explain": ["rocketry"], "rocketry": ["."], "Mercury": ["flights"], "flights": ["had", "."], "had": ["1", "3;", "2-man"], "1": ["astronaut"], "astronaut": ["Apollo"], "Apollo": ["had"], "3;": ["this"], "intermediate": ["program"], "program": ["had"], "2-man": ["flights"], "Hales": ["1844"], "1844": ["military"], "military": ["rocket", "target"], "using": ["curved"], "curved": ["vanes"], "vanes": ["stayed"], "stayed": ["stable"], "stable": ["by"], "doing": ["this"], "flight": ["."], "In": ["Dec", "1966"], "Dec": ["."], "1972": ["Gene"], "Gene": ["Cernan"], "Cernan": ["became"], "became": ["the"], "last": ["man"], "command": ["one"], "one": ["of"], "these": ["vehicles", "extra", "captured", "All-American"], "vehicles": ["known"], "known": ["as"], "as": ["the", "early", "1232", "atmospheric"], "LM": ["."], "To": ["leave"], "leave": ["Earths"], "Earths": ["orbit"], "orbit": ["a"], "must": ["accelerate"], "accelerate": ["to"], "25000": ["mph"], "mph": ["to"], "achieve": ["this"], "EV": ["for"], "short": ["."], "were": ["used"], "used": ["in", "these", "these"], "country": ["as"], "early": ["as", "inventions"], "1232": ["."], "Added": ["thrust"], "takeoffs": ["is"], "is": ["provided", "an"], "provided": ["by"], "extra": ["rockets"], "attached": ["to"], "After": ["World"], "World": ["War"], "War": ["II", "the"], "II": ["the"], "captured": ["German"], "German": ["rockets"], "atmospheric": ["probes"], "probes": ["."], "One": ["of"], "Goddards": ["early"], "inventions": ["was"], "into": ["this"], "anti-tank": ["rocket"], "gun": ["."], "Theyre": ["fired"], "fired": ["to"], "slow": ["down"], "down": ["the"], "movement": ["of"], "space": ["vehicle"], "vehicle": ["."], "Atlas": ["is"], "example": ["of"], "that": ["lifts"], "lifts": ["a"], "multistage": ["rocket"], "off": ["the"], "ground": ["."], "During": ["the"], "Gulf": ["War"], "All-American": ["missiles"], "missiles": ["to"], "intercept": ["Iraqs"], "Iraqs": ["Scuds"], "Scuds": ["."], "ICBM": ["which"], "which": ["stands"], "stands": ["for"], "can": ["deliver"], "deliver": ["a"], "payload": ["to"], "target": ["thousands"], "thousands": ["of"], "miles": ["away"], "away": ["."], "1966": ["the"], "government": ["awarded"], "awarded": ["his"], "his": ["heirs", "rocket"], "heirs": ["$1"], "$1": ["million"], "million": ["for"], "infringements": ["on"], "patents": ["."]}