{"After": ["renouncing"], "renouncing": ["polygamy"], "polygamy": ["this"], "this": ["admitted", "antislavery", ".", "chewy", "Puccini"], "admitted": ["to"], "to": ["Union", "label"], "Union": ["as"], "as": ["45th"], "45th": ["state"], "state": ["."], ".": [], "Death": ["claims"], "claims": ["this"], "antislavery": ["novelist"], "novelist": ["whose"], "whose": ["most"], "most": ["famous"], "famous": ["work"], "work": ["was"], "was": ["serialized"], "serialized": ["in"], "in": ["1851", "1746", "Turin"], "1851": ["."], "Founded": ["in"], "1746": ["the"], "the": ["College"], "College": ["of"], "of": ["New", "doomed"], "New": ["Jersey"], "Jersey": ["renames"], "renames": ["itself"], "itself": ["this"], "Using": ["his"], "his": ["daughter"], "daughter": ["Claras"], "Claras": ["nickname"], "nickname": ["to"], "label": ["it"], "it": ["Leo"], "Leo": ["Hirschfield"], "Hirschfield": ["introduces"], "introduces": ["this"], "chewy": ["roll"], "roll": ["."], "A": ["tale"], "tale": ["of"], "doomed": ["&"], "&": ["impoverished"], "impoverished": ["artists"], "artists": ["this"], "Puccini": ["opera"], "opera": ["premieres"], "premieres": ["in"], "Turin": ["."]}