{"A": ["plumber", "wing"], "plumber": ["uses"], "uses": ["one"], "one": ["to"], "to": ["clear"], "clear": ["out"], "out": ["your", "as"], "your": ["pipes"], "pipes": ["."], ".": [], "It": ["has"], "has": ["adjustable"], "adjustable": ["jaws"], "jaws": ["so"], "so": ["it"], "it": ["can", "didnt"], "can": ["grasp"], "grasp": ["nuts"], "nuts": ["of"], "of": ["different"], "different": ["sizes"], "sizes": ["."], "Its": ["a"], "a": ["moveable", "caterpillar"], "moveable": ["trestle"], "trestle": ["or"], "or": ["frame"], "frame": ["that"], "that": ["supports"], "supports": ["wood"], "wood": ["being"], "being": ["cut"], "cut": ["."], "wing": ["nut"], "nut": ["is", "."], "is": ["also"], "also": ["called"], "called": ["this;"], "this;": ["&"], "&": ["no"], "no": ["it"], "didnt": ["start"], "start": ["out"], "as": ["a"], "caterpillar": ["nut"]}