{"In": ["1882", "1828"], "1882": ["gunman"], "gunman": ["Charles"], "Charles": ["Guiteau"], "Guiteau": ["was"], "was": ["hanged", "shot", "ambushed", "killed"], "hanged": ["for"], "for": ["the", "independence"], "the": ["assassination", "Audubon", "Irish"], "assassination": ["of"], "of": ["this", "the", "his"], "this": ["man", "leader", "great"], "man": ["."], ".": [], "He": ["was"], "shot": ["in"], "in": ["February", "Harlem", "1922"], "February": ["1965"], "1965": ["while"], "while": ["giving"], "giving": ["a"], "a": ["speech", "servant"], "speech": ["at"], "at": ["the"], "Audubon": ["Ballroom"], "Ballroom": ["in"], "Harlem": ["."], "Played": ["on"], "on": ["screen"], "screen": ["by"], "by": ["Liam", "2"], "Liam": ["Neeson"], "Neeson": ["this"], "leader": ["of"], "Irish": ["struggle"], "struggle": ["for"], "independence": ["was"], "ambushed": ["&"], "&": ["killed", "a"], "killed": ["in", "by"], "1922": ["."], "1828": ["this"], "great": ["Zulu"], "Zulu": ["warrior"], "warrior": ["chief"], "chief": ["was"], "2": ["of"], "his": ["half-brothers"], "half-brothers": ["&"], "servant": ["."]}