{"Musca": ["domestica"], "domestica": ["is"], "is": ["the", "the"], "the": ["scientific", "defining", "U", "Latin"], "scientific": ["name"], "name": ["for"], "for": ["this", "this", "Pillager"], "this": ["ever-present", "body"], "ever-present": ["type"], "type": ["of"], "of": ["fly", "these", "water", "these"], "fly": [".", "named", "causes", "can"], ".": [], "The": ["structure", "fruit", "robber"], "structure": ["of"], "these": ["is", "from"], "defining": ["difference"], "difference": ["between"], "between": ["true"], "true": ["flies"], "flies": ["&", "."], "&": ["other", "a"], "other": ["insects"], "insects": ["called"], "called": ["flies", "nagana"], "fruit": ["fly"], "named": ["for"], "body": ["of"], "water": ["was"], "was": ["thought"], "thought": ["to"], "to": ["be"], "be": ["eradicated", "described"], "eradicated": ["in"], "in": ["the", "1930;", "humans", "cattle"], "U": ["."], "S": ["."], "1930;": ["oops"], "oops": ["."], "This": ["African"], "African": ["fly"], "causes": ["sleeping"], "sleeping": ["sickness"], "sickness": ["in"], "humans": ["&"], "a": ["similar"], "similar": ["ailment"], "ailment": ["called"], "nagana": ["in"], "cattle": ["."], "robber": ["or"], "or": ["assassin"], "assassin": ["fly"], "can": ["be"], "described": ["as"], "as": ["one"], "one": ["of"], "from": ["the"], "Latin": ["for"], "Pillager": ["."]}