{"One": ["book"], "book": ["calls"], "calls": ["her", "herself"], "her": ["works", "wedding", "1870s", "friend", "instead"], "a": ["stereotypical", "young", "curious", "fling", "married", "girl", "shy", "thief", "Thomas"], "stereotypical": ["nice"], "nice": ["girl;"], "girl;": ["we"], "we": ["wonder"], "wonder": ["how"], "how": ["Mark"], "Mark": ["Twain"], "Twain": ["would"], "would": ["have"], "have": ["answered"], "answered": ["that"], "that": [".", "cats"], ".": [], "Holland": ["is"], "is": ["the", "Muriel", "today", "the", "A", "the", "in", "the", "dismayed"], "the": ["last", "coming", "title", "altar", "selfish", "infamous", "beginning", "lusty", "heroine", "Santa"], "last": ["name"], "name": ["of"], "of": ["this", "age", "Esther", "her", "this", "this", "Tertius", "a", "emotion", "this", "Vanity", "the"], "this": ["character", "poets", "D", "title", "flowery", "Dickens", "knitter", "1973", "Becky"], "character": ["whose", "still"], "whose": ["life"], "life": ["was"], "was": ["chronicled", "once"], "chronicled": ["by"], "by": ["Wendy", "experience"], "Wendy": ["Wasserstein"], "Wasserstein": ["."], "In": ["this"], "poets": ["only"], "only": ["novel"], "novel": ["The", ".", "Middlemarch", "she"], "The": ["Bell"], "Bell": ["Jar"], "Jar": ["she"], "she": ["related", "is"], "related": ["the"], "coming": ["of"], "age": ["of"], "Esther": ["Greenwood"], "Greenwood": ["."], "Miranda": ["a"], "young": ["woman"], "woman": ["appears", "."], "appears": ["in", "peering"], "in": ["several", "Villette", "her", "Tom"], "several": ["of"], "works": ["including"], "including": ["Pale"], "Pale": ["Horse", "Rider"], "Horse": ["Pale"], "Rider": ["."], "This": ["Scottish", "Defoe", "Nabokov", "title", "Sue"], "Scottish": ["teacher"], "teacher": ["&", "Lucy"], "&": ["spinster", "I", "Gudrun", "is"], "spinster": ["is"], "Muriel": ["Sparks"], "Sparks": ["most"], "most": ["famous"], "famous": ["creation"], "creation": ["."], "Her": ["lines"], "lines": ["include"], "include": ["What"], "What": ["a", "do"], "curious": ["feeling"], "feeling": ["!"], "!": [], "How": ["queer"], "queer": ["everything"], "everything": ["is"], "today": ["!"], "I": ["didnt"], "didnt": ["know"], "know": ["that"], "cats": ["could"], "could": ["grin"], "grin": ["."], "Ursula": ["&"], "Gudrun": ["Brangwen"], "Brangwen": ["are"], "are": ["the"], "title": ["women", "woman", "heroine"], "women": ["of"], "D": ["."], "H": ["."], "Lawrence": ["novel"], "Theodore": ["Dreisers"], "Dreisers": ["own"], "own": ["sister"], "sister": ["Emma"], "Emma": ["had"], "had": ["a", "many"], "fling": ["with"], "with": ["a", "Mr"], "married": ["man"], "man": ["helping"], "helping": ["inspire"], "inspire": ["this"], "Frederick": ["Winterbourne"], "Winterbourne": ["had"], "many": ["thoughts"], "thoughts": ["of"], "flowery": ["Henry"], "Henry": ["James"], "James": ["girl"], "girl": [".", "this"], "Left": ["at"], "at": ["the"], "altar": ["as"], "as": ["a", "the"], "Dickens": ["character"], "still": ["wears"], "wears": ["her"], "wedding": ["dress"], "dress": ["."], "She": ["wrote"], "wrote": ["about"], "about": ["shy"], "shy": ["teacher", "governess"], "Lucy": ["Snowe"], "Snowe": ["in"], "Villette": ["after"], "after": ["creating"], "creating": ["a"], "governess": ["named"], "named": ["Jane"], "Jane": ["Eyre"], "Eyre": ["."], "Rosamond": ["Vincy"], "Vincy": ["is"], "selfish": ["spouse"], "spouse": ["of"], "Tertius": ["Lydgate"], "Lydgate": ["in"], "1870s": ["novel"], "Middlemarch": ["."], "Defoe": ["heroine"], "heroine": ["calls", "of", "of", "tries"], "herself": ["As"], "As": ["impudent"], "impudent": ["a"], "thief": ["."], "infamous": ["Moll"], "Moll": ["Cut-Purse"], "Cut-Purse": ["."], "At": ["the"], "beginning": ["of"], "Thomas": ["Hardy"], "Hardy": ["novel"], "A": ["mere"], "mere": ["vessel"], "vessel": ["of"], "emotion": ["untinctured"], "untinctured": ["by"], "experience": ["."], "Asked": ["What"], "do": ["you"], "you": ["make"], "make": ["madame"], "madame": ["?"], "?": [], "knitter": ["replied"], "replied": ["Many"], "Many": ["things"], "things": ["."], "for": ["instance"], "instance": ["shrouds"], "shrouds": ["."], "Nabokov": ["nymphet"], "nymphet": ["first"], "first": ["appears"], "peering": ["over"], "over": ["dark"], "dark": ["glasses"], "glasses": ["."], "Isadora": ["Wing"], "Wing": ["is"], "lusty": ["heroine"], "1973": ["Erica"], "Erica": ["Jong"], "Jong": ["bestseller"], "bestseller": ["."], "Becky": ["Thatcher", "is"], "Thatcher": ["is"], "Tom": ["Sawyer;"], "Sawyer;": ["this"], "Vanity": ["Fair"], "Fair": ["."], "tries": ["to"], "to": ["set", "her"], "set": ["up"], "up": ["her"], "friend": ["Harriet"], "Harriet": ["with"], "Mr": ["."], "Elton": ["&", "proposes"], "dismayed": ["when"], "when": ["Elton"], "proposes": ["to"], "instead": ["."], "Sue": ["Grafton"], "Grafton": ["detective"], "detective": ["was"], "once": ["part"], "part": ["of"], "Santa": ["Teresa"], "Teresa": ["Police"], "Police": ["Department"], "Department": ["."]}