{"Hud": ["."], ".": [], "Dr": ["."], "Strangelove": ["."], "Saving": ["Private"], "Private": ["Ryan"], "Ryan": ["."], "Whats": ["Eating"], "Eating": ["Gilbert"], "Gilbert": ["Grape"], "Grape": ["?"], "?": [], "The": ["Good"], "Good": ["the"], "the": ["Bad", "Ugly"], "Bad": ["&"], "&": ["the", "Hooch"], "Ugly": ["(all"], "(all": ["3"], "3": ["per"], "per": ["favore)"], "favore)": ["."], "Lawrence": ["of"], "of": ["Arabia"], "Arabia": ["."], "Turner": ["&", "please)"], "Hooch": ["(just"], "(just": ["Turner"], "please)": ["."], "Fantastic": ["Mr"], "Mr": ["."], "Fox": ["."], "Peggy": ["Sue"], "Sue": ["Got"], "Got": ["Married"], "Married": ["."], "Mary": ["Reilly"], "Reilly": ["."]}