{"1787:": ["This"], "This": ["state"], "state": ["becomes"], "becomes": ["the", "the", "the"], "the": ["first", "Constitution", "first", "U", "first"], "first": ["to", "European", "U"], "to": ["ratify", "describe", "be"], "ratify": ["the"], "Constitution": ["."], ".": [], "1678:": ["Louis"], "Louis": ["Hennepin"], "Hennepin": ["becomes"], "European": ["to"], "describe": ["this"], "this": ["landmark", "hyphenated", "way", "one"], "landmark": ["on"], "on": ["the", "this"], "U": [".", ".", "."], "S": [".", ".", "."], "-Canada": ["border"], "border": ["."], "1917:": ["The"], "The": ["U"], "declares": ["war"], "war": ["on"], "hyphenated": ["kingdom"], "kingdom": ["."], "1982:": ["At"], "At": ["a"], "a": ["Texas"], "Texas": ["prison"], "prison": ["murderer"], "murderer": ["Charlie"], "Charlie": ["Brooks"], "Brooks": ["becomes"], "prisoner": ["to"], "be": ["executed"], "executed": ["this"], "way": ["."], "1972:": ["Americas"], "Americas": ["last"], "last": ["lunar"], "lunar": ["landing"], "landing": ["mission"], "mission": ["this"], "one": ["blasts"], "blasts": ["off"], "off": ["from"], "from": ["Cape"], "Cape": ["Canaveral"], "Canaveral": ["."]}