{"Ancient": ["Persian"], "Persian": ["priests"], "priests": ["like"], "like": ["those"], "those": ["who"], "who": ["visited"], "visited": ["the"], "the": ["baby", "Polish", "Italian"], "baby": ["Jesus"], "Jesus": ["."], ".": [], "A": ["Welsh", "Hindu"], "Welsh": ["dog"], "dog": ["breed"], "breed": ["with"], "with": ["a", "meat"], "a": ["fox-like", "Yankees", "baked"], "fox-like": ["head"], "head": ["."], "Hindu": ["holy"], "holy": ["man"], "man": ["or"], "or": ["a"], "Yankees": ["great"], "great": ["."], "From": ["the"], "Polish": ["for"], "for": ["dumpling"], "dumpling": ["its"], "its": ["a"], "baked": ["turnover"], "turnover": ["with"], "meat": ["inside"], "inside": ["."], "Its": ["the"], "Italian": ["version"], "version": ["of"], "of": ["Louis"], "Louis": ["."]}