{"The": ["genus", "swallowtail"], "genus": ["name", "name", "papilio;", "vulpes;"], "name": ["of", "of"], "of": ["the", "wisdom", "the", "this", "this", "the"], "the": ["burrowing", "appropriate", "Sumatran", "dog", "genus"], "burrowing": ["owl"], "owl": ["is"], "is": ["this", "the", "genus", "French", "in"], "this": ["Greek", "animal", "is"], "Greek": ["goddess"], "goddess": ["of"], "wisdom": ["."], ".": [], "Dicerorhinus": ["is"], "appropriate": ["genus"], "Sumatran": ["type"], "type": ["of", "of"], "animal": ["which", "."], "which": ["has"], "has": ["2"], "2": ["horns"], "horns": ["."], "swallowtail": ["type"], "papilio;": ["makes"], "makes": ["sense"], "sense": ["since"], "since": ["papillon"], "papillon": ["is"], "French": ["for"], "for": ["it"], "it": ["."], "This": ["carnivore"], "carnivore": ["of"], "dog": ["family"], "family": ["is"], "in": ["the"], "vulpes;": ["vulpine"], "vulpine": ["means"], "means": ["to"], "to": ["resemble"], "resemble": ["that"], "that": ["animal"]}