{"The": ["proverb", "theater"], "proverb": ["Dont"], "Dont": ["cry"], "cry": ["over"], "over": ["this"], "this": ["has", "than", "often", "term"], "has": ["been"], "been": ["around"], "around": ["since"], "since": ["at"], "at": ["least"], "least": ["1659"], "1659": ["."], ".": [], "You": ["can"], "can": ["catch"], "catch": ["more"], "more": ["flies"], "flies": ["with"], "with": ["this", "vinegar"], "than": ["with"], "vinegar": ["."], "theater": ["area"], "area": ["nicknamed"], "nicknamed": ["this"], "often": ["held"], "held": ["the"], "the": ["cheapest", "rear", "balcony", "bough"], "cheapest": ["seats"], "seats": ["usually"], "usually": ["those"], "those": ["in"], "in": ["the"], "rear": ["of"], "of": ["the", "verses"], "balcony": ["."], "A": ["book", "pig"], "book": ["of"], "verses": ["underneath"], "underneath": ["the"], "bough": ["these"], "these": ["2"], "2": ["things--and"], "things--and": ["thou"], "thou": ["."], "pig": ["product"], "product": ["gave"], "gave": ["us"], "us": ["this"], "term": ["meaning"], "meaning": ["clumsy"], "clumsy": ["or"], "or": ["inept"], "inept": ["."]}