{"Developed": ["in"], "in": ["the", "the", "1763", "the", "Rhode"], "the": ["1850s", "Rhode", "U", "oldest", "U"], "1850s": ["the"], "Rhode": ["Island", "Island", "Island", "Islands"], "Island": ["Red", "has", "."], "Red": ["made"], "made": ["raising"], "raising": ["of"], "of": ["these", "worship", "this", "Rhode"], "these": ["a"], "a": ["major", "national"], "major": ["industry"], "industry": ["in"], "U": [".", "."], ".": [], "S": [".", "."], "While": ["Ocean"], "Ocean": ["State"], "State": ["appears"], "appears": ["on"], "on": ["its", "this"], "its": ["license", "founder"], "license": ["plates"], "plates": ["this"], "this": ["diminutive", "man", "religion", "bay"], "diminutive": ["nickname"], "nickname": ["is"], "is": ["also", "in"], "also": ["widely"], "widely": ["used"], "used": ["."], "has": ["a"], "national": ["memorial"], "memorial": ["honoring"], "honoring": ["this"], "man": ["its"], "founder": ["."], "Built": ["in"], "1763": ["the"], "oldest": ["existing"], "existing": ["house"], "house": ["of"], "worship": ["of"], "religion": ["in"], "All": ["5"], "5": ["of"], "Islands": ["counties"], "counties": ["are"], "are": ["on"], "bay": ["."]}