{"It": ["was"], "was": ["4", "knighted", "named", "that"], "4": ["years"], "years": ["ago"], "ago": ["(not"], "(not": ["today)"], "today)": ["that"], "that": ["this", "became", "night"], "this": ["musician", "50s"], "musician": ["was"], "knighted": ["."], ".": [], "You": ["may"], "may": ["remember"], "remember": ["this"], "50s": ["senator"], "senator": ["from"], "from": ["Wisconsin", "such"], "Wisconsin": ["from"], "such": ["witch-hunts"], "witch-hunts": ["as"], "as": ["The"], "The": ["Red", "Northern"], "Red": ["Scare"], "Scare": ["."], "This": ["legendary"], "legendary": ["lefty"], "lefty": ["might"], "might": ["say"], "say": ["Are"], "Are": ["you"], "you": ["blind", "dont"], "blind": ["?"], "?": [], "!": [], "I": ["won", "am", "cremated"], "won": ["Wimbledon"], "Wimbledon": ["in"], "in": ["84", "1964;", "dictionaries", "the"], "84": ["&"], "&": ["you", "LBJs"], "dont": ["know"], "know": ["who"], "who": ["I"], "am": ["?"], "Dont": ["find"], "find": ["it"], "it": ["Strange"], "Strange": ["wed"], "wed": ["ask"], "ask": ["about"], "about": ["him"], "him": ["JFK", ".", "."], "JFK": ["&"], "LBJs": ["Secretary"], "Secretary": ["of"], "of": ["Defense", "advancement", "many"], "Defense": ["."], "He": ["penned"], "penned": ["Understanding"], "Understanding": ["Media"], "Media": ["in"], "1964;": ["we"], "we": ["got"], "got": ["the"], "the": ["message", "New", "strut", "queerest"], "message": ["."], "New": ["in", "Hampshire"], "dictionaries": ["its"], "its": ["low-paying", "the"], "low-paying": ["employment"], "employment": ["with"], "with": ["no"], "no": ["hope"], "hope": ["of"], "advancement": ["."], "On": ["Feb"], "Feb": ["."], "1": ["2000"], "2000": ["he"], "he": ["defeated"], "defeated": ["George"], "George": ["W"], "W": ["."], "Bush": ["in"], "Hampshire": ["primary"], "primary": ["."], "A": ["spring"], "spring": ["wrapped"], "wrapped": ["around"], "around": ["a"], "a": ["shock", "sound", "center"], "shock": ["absorber"], "absorber": ["its"], "strut": ["system"], "system": ["of"], "many": ["front-wheel-drive"], "front-wheel-drive": ["vehicles"], "vehicles": ["."], "In": ["1841"], "1841": ["a"], "sound": ["that"], "became": ["a"], "center": ["for"], "for": ["Antarctic", "him"], "Antarctic": ["exploration"], "exploration": ["was"], "named": ["for"], "Northern": ["Lights"], "Lights": ["have"], "have": ["seen"], "seen": ["queer"], "queer": ["sights"], "sights": ["but"], "but": ["the"], "queerest": ["they"], "they": ["ever"], "ever": ["did"], "did": ["see"], "see": ["was"], "night": ["."], "cremated": ["him"]}