{"In": ["1776", "The", "a", "1774"], "1776": ["he"], "he": ["told", "wrote", "asked"], "told": ["the"], "the": ["Continental", "word", "final", "price"], "Continental": ["Army"], "Army": ["that"], "that": ["it"], "it": ["must"], "must": ["resolve"], "resolve": ["to"], "to": ["conquer", "enslave", "set", "be"], "conquer": ["or"], "or": ["die", "peace", "sink", "die", "perish"], "die": [".", "survive"], ".": [], "Jeffersons": ["first"], "first": ["draft"], "draft": ["of", "used"], "of": ["this", "chains"], "this": ["used", "Italian"], "used": ["the", "unalienable"], "word": ["inalienable;"], "inalienable;": ["the"], "final": ["draft"], "unalienable": ["."], "The": ["American"], "American": ["Crisis"], "Crisis": ["he"], "wrote": ["We"], "We": ["fight"], "fight": ["not"], "not": ["to"], "enslave": ["but"], "but": ["to"], "set": ["a"], "a": ["country", "1775"], "country": ["free", "."], "free": ["."], "1775": ["speech"], "speech": ["he"], "asked": ["Is"], "Is": ["life"], "life": ["so"], "so": ["dear", "sweet"], "dear": ["or"], "peace": ["so"], "sweet": ["as"], "as": ["to"], "be": ["purchased"], "purchased": ["at"], "at": ["the"], "price": ["of"], "chains": ["and"], "and": ["slavery"], "slavery": ["?"], "?": [], "1774": ["John"], "John": ["Adams"], "Adams": ["said"], "said": ["I"], "I": ["have"], "have": ["passed"], "passed": ["this"], "Italian": ["river;"], "river;": ["swim"], "swim": ["or"], "sink": ["live"], "live": ["or"], "survive": ["or"], "perish": ["with"], "with": ["my"], "my": ["country"]}