{"Nocturnal": ["Fears"], "Fears": ["a"], "a": ["proposed", "script", "barbed-wire"], "proposed": ["sequel", "third"], "sequel": ["to"], "to": ["this", "film", "a"], "this": ["wouldve", "School", "series", "John", "surrealist"], "wouldve": ["seen", "seen"], "seen": ["Elliot", "the"], "Elliot": ["kidnapped"], "kidnapped": ["by"], "by": ["aliens;"], "aliens;": ["Spielberg"], "Spielberg": ["said"], "said": ["N-O", "no"], "N-O": ["."], ".": [], "Warner": ["Bros"], "Bros": [".", "."], "Green": ["Lantern"], "Lantern": ["missed"], "missed": ["the"], "the": ["green", "lead", "title", "project", "Marx"], "green": ["light"], "light": ["after"], "after": ["fan"], "fan": ["outcry"], "outcry": ["over"], "over": ["this"], "School": ["of"], "of": ["Rock", "this"], "Rock": ["guy"], "guy": ["as"], "as": ["the"], "lead": ["."], "A": ["proposed"], "third": ["film"], "film": ["in", "versions"], "in": ["this", "Hell"], "series": ["wouldve"], "title": ["guys"], "guys": ["in"], "Hell": ["but"], "but": ["Bill"], "Bill": ["Murray"], "Murray": ["slimed"], "slimed": ["the"], "project": ["."], "John": ["Candy", "Belushi", "Kennedy"], "Candy": ["John"], "Belushi": ["&"], "&": ["Chris"], "Chris": ["Farley"], "Farley": ["have"], "have": ["all"], "all": ["been"], "been": ["linked"], "linked": ["to"], "versions": ["of"], "Kennedy": ["Toole"], "Toole": ["novel"], "novel": ["."], "Groucho": ["said"], "no": ["to"], "script": ["this"], "surrealist": ["wrote"], "wrote": ["for"], "for": ["the"], "Marx": ["Bros"], ";": ["he"], "he": ["sent"], "sent": ["Harpo"], "Harpo": ["a"], "barbed-wire": ["harp"], "harp": ["anyway"], "anyway": ["."]}