{"Thousands": ["receive"], "receive": ["care"], "care": ["every"], "every": ["year"], "year": ["at"], "at": ["this", "Fort"], "this": ["institution", "region", "city", "great"], "institution": ["for"], "for": ["homeless"], "homeless": ["neglected"], "neglected": ["&"], "&": ["abused"], "abused": ["children"], "children": ["founded"], "founded": ["in"], "in": ["1917", "1803"], "1917": ["."], ".": [], "With": ["the"], "the": ["purchase", "area", "United", "territorial", "U"], "purchase": ["of"], "of": ["this", "the"], "region": ["in"], "1803": ["the"], "area": ["now"], "now": ["known"], "known": ["as"], "as": ["Nebraska"], "Nebraska": ["became"], "became": ["part"], "part": ["of"], "United": ["States"], "States": ["."], "In": ["1982"], "1982": ["Nebraskans"], "Nebraskans": ["passed"], "passed": ["Initiative"], "Initiative": ["300"], "300": ["banning"], "banning": ["out-of-state"], "out-of-state": ["corporations"], "corporations": ["from"], "from": ["buying"], "buying": ["these"], "these": ["."], "From": ["1855"], "1855": ["to"], "to": ["1867", "the"], "1867": ["this"], "city": ["was"], "was": ["the"], "territorial": ["capital"], "capital": ["."], "On": ["May"], "May": ["6"], "6": ["1877"], "1877": ["this"], "great": ["Sioux"], "Sioux": ["Indian"], "Indian": ["chief"], "chief": ["surrendered"], "surrendered": ["to"], "U": ["."], "S": ["."], "Army": ["at"], "Fort": ["Robinson"], "Robinson": ["."]}