{"Belonging": ["to"], "to": ["him", "see"], "him": ["."], ".": [], "Richard": ["Burtons"], "Burtons": ["wife"], "wife": ["twice"], "twice": ["."], "Slang": ["for"], "for": ["any", "it"], "any": ["line"], "line": ["of"], "of": ["work", "the"], "work": ["."], "A": ["womans"], "womans": ["title"], "title": ["&"], "&": ["a"], "a": ["womens"], "womens": ["magazine"], "magazine": ["."], "Meaning": ["namely"], "namely": ["its"], "its": ["an"], "an": ["abbreviation"], "abbreviation": ["of"], "the": ["Latin"], "Latin": ["for"], "it": ["is"], "is": ["permitted"], "permitted": ["to"], "see": ["."]}