{"While": ["Secretary", "Secretary"], "Secretary": ["of", "of", "of", "of", "of", "of"], "of": ["State", "State", "State", "State", "State", "War"], "State": ["from", "from", "Martin", "John", "he"], "from": ["1811", "1801", "1809"], "1811": ["to"], "to": ["1817", "1809", "1817", "govern", "the"], "1817": ["he", "."], "he": ["might", "was", "was"], "might": ["have"], "have": ["been"], "been": ["asked"], "asked": ["Whats"], "Whats": ["up"], "up": ["doctrine"], "doctrine": ["?"], "?": [], ".": [], "1801": ["to"], "1809": ["he", "to"], "was": ["president", "Andrew"], "president": ["from"], "Through": ["skillful"], "skillful": ["negotiation"], "negotiation": ["Secretary"], "Martin": ["Van"], "Van": ["Buren"], "Buren": ["got"], "got": ["the"], "the": ["U", "U"], "U": [".", "."], "S": [".", "."], "this": ["trade", "country"], "trade": ["status"], "status": ["with"], "with": ["Turkey"], "Turkey": ["."], "As": ["Secretary"], "John": ["Quincy"], "Quincy": ["Adams"], "Adams": ["told"], "told": ["this"], "country": ["to"], "govern": ["Florida"], "Florida": ["better"], "better": ["or"], "or": ["cede"], "cede": ["it"], "it": ["to"], "He": ["wasnt"], "wasnt": ["a"], "a": ["Secretary"], "Andrew": ["Johnsons"], "Johnsons": ["Secretary"], "War": ["in"], "in": ["1867"], "1867": ["&"], "&": ["1868"], "1868": ["."]}