{"In": ["the"], "the": ["N", "end", "tallest", "sea", "only"], "N": ["."], ".": [], "American": ["species", "bird"], "species": ["of", "of", "of", "of"], "of": ["this", "microscopic", "each", "nearly", "this", "this", "this"], "this": ["mammal", "migrate", "small", "native"], "mammal": ["there"], "there": ["are"], "are": ["hundreds"], "hundreds": ["of"], "microscopic": ["barbs"], "barbs": ["at"], "at": ["the"], "end": ["of"], "each": ["quill"], "quill": ["."], "Known": ["as"], "as": ["a", "a"], "a": ["whooper", "height", "pet", "species"], "whooper": ["its"], "its": ["the", "clean"], "tallest": ["North"], "North": ["American"], "bird": ["reaching"], "reaching": ["a"], "height": ["of"], "nearly": ["5"], "5": ["feet"], "feet": ["."], "When": ["rainbow"], "rainbow": ["species"], "migrate": ["to"], "to": ["the", "silver;", "care", "Central", "living"], "sea": ["their"], "their": ["color"], "color": ["changes"], "changes": ["to"], "silver;": ["theyre"], "theyre": ["then"], "then": ["called"], "called": ["steelheads"], "steelheads": ["."], "The": ["golden", "Yapok"], "golden": ["species"], "small": ["rodent"], "rodent": ["is"], "is": ["often", "the"], "often": ["sold"], "sold": ["as"], "pet": ["because"], "because": ["its"], "clean": ["&"], "&": ["easy", "South"], "easy": ["to"], "care": ["for"], "for": ["."], "Yapok": ["a"], "native": ["to"], "Central": ["&"], "South": ["America"], "America": ["is"], "only": ["marsupial"], "marsupial": ["adapted"], "adapted": ["to"], "living": ["in"], "in": ["water"], "water": ["."]}